databricks/__init__.py
databricks/labs/__init__.py
databricks/labs/community/__about__.py
databricks/labs/community/__init__.py
databricks/labs/community/transpiler/__init__.py
databricks/labs/community/transpiler/common_types.py
databricks/labs/community/transpiler/dialect_utils.py
databricks/labs/community/transpiler/helpers.py
databricks/labs/community/transpiler/lca_utils.py
databricks/labs/community/transpiler/local_expression.py
databricks/labs/community/transpiler/server.py
databricks/labs/community/transpiler/transpiler.py
databricks/labs/community/transpiler/generator/__init__.py
databricks/labs/community/transpiler/generator/databricks.py
databricks/labs/community/transpiler/parsers/__init__.py
databricks/labs/community/transpiler/parsers/oracle.py
databricks/labs/community/transpiler/parsers/presto.py
databricks/labs/community/transpiler/parsers/snowflake.py
databricks_labs_remorph_community_transpiler-0.0.1.dist-info/METADATA
databricks_labs_remorph_community_transpiler-0.0.1.dist-info/WHEEL
databricks_labs_remorph_community_transpiler-0.0.1.dist-info/licenses/LICENSE
databricks_labs_remorph_community_transpiler-0.0.1.dist-info/licenses/NOTICE
databricks_labs_remorph_community_transpiler-0.0.1.dist-info/RECORD
