Metadata-Version: 2.4
Name: databricks-labs-remorph-community-transpiler
Version: 0.0.1
Summary: SQL code converter and data reconcilation tool for accelerating data onboarding to Databricks from EDW, CDW and other ETL sources.
Project-URL: Documentation, https://github.com/databrickslabs/remorph-community-transpiler
Project-URL: Issues, https://github.com/databrickslabs/remorph-community-transpiler/issues
Project-URL: Source, https://github.com/databrickslabs/remorph-community-transpiler
License-File: LICENSE
License-File: NOTICE
Keywords: Databricks,Oracle,Remorph,Snowflake,T-SQL,Teradata,Transpiler
Classifier: Development Status :: 3 - Alpha
Classifier: Programming Language :: Python :: 3.10
Classifier: Programming Language :: Python :: 3.11
Classifier: Programming Language :: Python :: Implementation :: CPython
Requires-Python: >=3.10
Requires-Dist: pygls>=2.0.0a2
Requires-Dist: pyyaml>=6.0.2
Requires-Dist: sqlglot==26.9.0
